example_project/__init__.py
example_project/settings.py
example_project/urls.py
example_project/wsgi.py
hordak/__init__.py
hordak/admin.py
hordak/apps.py
hordak/defaults.py
hordak/exceptions.py
hordak/resources.py
hordak/urls.py
hordak/data_sources/__init__.py
hordak/data_sources/tellerio.py
hordak/fixtures/top-level-accounts.json
hordak/forms/__init__.py
hordak/forms/accounts.py
hordak/forms/statement_csv_import.py
hordak/forms/transactions.py
hordak/management/__init__.py
hordak/management/commands/__init__.py
hordak/management/commands/create_chart_of_accounts.py
hordak/migrations/0001_initial.py
hordak/migrations/0002_check_leg_trigger_20160903_1149.py
hordak/migrations/0003_check_zero_amount_20160907_0921.py
hordak/migrations/0004_auto_20161113_1932.py
hordak/migrations/0005_account_currencies.py
hordak/migrations/0006_auto_20161209_0108.py
hordak/migrations/0007_auto_20161209_0111.py
hordak/migrations/0008_auto_20161209_0129.py
hordak/migrations/0009_bank_accounts_are_asset_accounts.py
hordak/migrations/0010_auto_20161216_1202.py
hordak/migrations/0011_auto_20170225_2222.py
hordak/migrations/0012_account_full_code.py
hordak/migrations/0013_trigger_full_account_code.py
hordak/migrations/0014_auto_20170302_1944.py
hordak/migrations/0015_auto_20170302_2109.py
hordak/migrations/0016_check_account_type.py
hordak/migrations/0017_auto_20171203_1516.py
hordak/migrations/0018_auto_20171205_1256.py
hordak/migrations/0019_statementimport_source.py
hordak/migrations/0020_auto_20171205_1424.py
hordak/migrations/0021_auto_20180329_1426.py
hordak/migrations/0022_auto_20180825_1026.py
hordak/migrations/0023_auto_20180825_1029.py
hordak/migrations/0024_auto_20180827_1148.py
hordak/migrations/0025_auto_20180829_1605.py
hordak/migrations/0026_auto_20190723_0929.py
hordak/migrations/0027_trigger_update_full_account_codes_effective.py
hordak/migrations/0028_auto_20220215_1847.py
hordak/migrations/0029_alter_leg_amount_currency_and_more.py
django_hordak-1.15.0.dist-info/LICENSE.txt
django_hordak-1.15.0.dist-info/METADATA
django_hordak-1.15.0.dist-info/WHEEL
django_hordak-1.15.0.dist-info/top_level.txt
django_hordak-1.15.0.dist-info/RECORD
