Metadata-Version: 2.1
Name: django-hordak
Version: 1.15.0
Summary: Double entry book keeping in Django
Home-page: https://github.com/adamcharnock/django-hordak
Author: Adam Charnock
Author-email: adam@adamcharnock.com
License: MIT
License-File: LICENSE.txt
Requires-Dist: django (>=1.10)
Requires-Dist: django-mptt (>=0.8)
Requires-Dist: django-model-utils (>=2.5.0)
Requires-Dist: dj-database-url (>=0.4.1)
Requires-Dist: django-extensions (>=1.7.3)
Requires-Dist: django-smalluuid (>=1.2.1)
Requires-Dist: requests (>=2)
Requires-Dist: django-money (>=0.9.1)
Requires-Dist: django-import-export (>=0.5.0)
Requires-Dist: babel (>=2.9.1)
Requires-Dist: openpyxl (<=2.6) ; python_version < "3.5"
Provides-Extra: subqueries
Requires-Dist: django-sql-utils ; extra == 'subqueries'
